django_cash_register/__init__.py
django_cash_register/admin.py
django_cash_register/apps.py
django_cash_register/fields.py
django_cash_register/forms.py
django_cash_register/functions.py
django_cash_register/models.py
django_cash_register/urls.py
django_cash_register/validators.py
django_cash_register/views.py
django_cash_register/migrations/0001_initial.py
django_cash_register/migrations/__init__.py
django_cash_register/static/css/style.css
django_cash_register/static/images/defaul_image.png
django_cash_register/static/js/cart_get_items.js
django_cash_register/static/js/cart_update.js
django_cash_register/static/js/jquery.js
django_cash_register/templates/admin/django_cash_register/change_form_object_tools.html
django_cash_register/templates/django_cash_register/base.html
django_cash_register/templates/django_cash_register/cart.html
django_cash_register/templates/django_cash_register/head.html
django_cash_register/templates/django_cash_register/header.html
django_cash_register/templates/django_cash_register/index.html
django_cash_register/templates/django_cash_register/links.html
django_cash_register/templates/django_cash_register/login.html
django_cash_register/templates/django_cash_register/scripts.html
django_cash_register/templates/django_cash_register/total.html
django_cash_register-0.2.3.dist-info/LICENSE
django_cash_register-0.2.3.dist-info/METADATA
django_cash_register-0.2.3.dist-info/WHEEL
django_cash_register-0.2.3.dist-info/top_level.txt
django_cash_register-0.2.3.dist-info/RECORD
